mm_device_adapters/__init__.py
mm_device_adapters/libs/AB_ALC_REV64.dll
mm_device_adapters/libs/AB_ASDx64.dll
mm_device_adapters/libs/BUF_USBCCDCamera_SDK_MM.dll
mm_device_adapters/libs/BufferCameraUsbLib.dll
mm_device_adapters/libs/FxLib.dll
mm_device_adapters/libs/KURIOS_COMMAND_LIB_Win64.dll
mm_device_adapters/libs/LaserCombinerSDK64.dll
mm_device_adapters/libs/LightEngineAPI.dll
mm_device_adapters/libs/LumencorDLL64.dll
mm_device_adapters/libs/MMConfig_demo.cfg
mm_device_adapters/libs/MMCoreJ_wrap.dll
mm_device_adapters/libs/OmicronxXDevices64.dll
mm_device_adapters/libs/PCO_Kamlib64.dll
mm_device_adapters/libs/PDL2000.dll
mm_device_adapters/libs/PiUsb.dll
mm_device_adapters/libs/ROEobsTools.dll
mm_device_adapters/libs/SiUSBXp.dll
mm_device_adapters/libs/SysInfo.dll
mm_device_adapters/libs/XCLIBW64.dll
mm_device_adapters/libs/atmcd64d.dll
mm_device_adapters/libs/hidapi.dll
mm_device_adapters/libs/hrfw64.dll
mm_device_adapters/libs/inpoutx64.dll
mm_device_adapters/libs/libdc1394-22.dll
mm_device_adapters/libs/libserialport.dll
mm_device_adapters/libs/mcam64.dll
mm_device_adapters/libs/mcammr64.dll
mm_device_adapters/libs/mmgr_dal_89North_LDI.dll
mm_device_adapters/libs/mmgr_dal_AAAOTF.dll
mm_device_adapters/libs/mmgr_dal_ABSCamera.dll
mm_device_adapters/libs/mmgr_dal_AOTF.dll
mm_device_adapters/libs/mmgr_dal_ASIFW1000.dll
mm_device_adapters/libs/mmgr_dal_ASIStage.dll
mm_device_adapters/libs/mmgr_dal_ASITiger.dll
mm_device_adapters/libs/mmgr_dal_ASIwptr.dll
mm_device_adapters/libs/mmgr_dal_AgilentLaserCombiner.dll
mm_device_adapters/libs/mmgr_dal_Aladdin.dll
mm_device_adapters/libs/mmgr_dal_AlliedVisionCamera.dll
mm_device_adapters/libs/mmgr_dal_AmScope.dll
mm_device_adapters/libs/mmgr_dal_Andor.dll
mm_device_adapters/libs/mmgr_dal_AndorDragonfly.dll
mm_device_adapters/libs/mmgr_dal_AndorILE.dll
mm_device_adapters/libs/mmgr_dal_AndorLaserCombiner.dll
mm_device_adapters/libs/mmgr_dal_AndorSDK3.dll
mm_device_adapters/libs/mmgr_dal_AndorShamrock.dll
mm_device_adapters-73.2025.3.28.dist-info/licenses/LICENSE
mm_device_adapters-73.2025.3.28.dist-info/METADATA
mm_device_adapters-73.2025.3.28.dist-info/WHEEL
mm_device_adapters-73.2025.3.28.dist-info/top_level.txt
mm_device_adapters-73.2025.3.28.dist-info/RECORD
