Metadata-Version: 2.4
Name: mm-device-adapters
Version: 73.2025.3.28
Summary: Pre-compiled device adapters for Micro-Manager
Author-email: Talley Lambert <talley.lambert@gmail.com>
License-Expression: LGPL-2.1-only
Requires-Python: >=3.9
License-File: LICENSE
Dynamic: license-file
